somecomfort/__init__.py
somecomfort/__main__.py
somecomfort/client.py
ha_somecomfort-0.6.2.dist-info/LICENSE
ha_somecomfort-0.6.2.dist-info/METADATA
ha_somecomfort-0.6.2.dist-info/WHEEL
ha_somecomfort-0.6.2.dist-info/entry_points.txt
ha_somecomfort-0.6.2.dist-info/top_level.txt
ha_somecomfort-0.6.2.dist-info/RECORD
